apimon/__init__.py
apimon/prometheus_init.py
apimon-0.0.3.dist-info/LICENSE
apimon-0.0.3.dist-info/METADATA
apimon-0.0.3.dist-info/WHEEL
apimon-0.0.3.dist-info/top_level.txt
apimon-0.0.3.dist-info/RECORD
