Metadata-Version: 2.1
Name: apimon
Version: 0.0.3
Summary: monitor apis metrics
Home-page: UNKNOWN
Author: yangwb
License: UNKNOWN
Platform: UNKNOWN
Classifier: Programming Language :: Python :: 3
Classifier: License :: OSI Approved :: MIT License
Classifier: Operating System :: OS Independent
License-File: LICENSE
Requires-Dist: flask (>=1.0.2)
Requires-Dist: prometheus-client (>=0.5.0)
